{
  "data_points": [
    {
      "date": "2025-10-28",
      "value": 0,
      "label": "Article Generation Trend",
      "category": "articles"
    },
    {
      "date": "2025-10-29",
      "value": 0,
      "label": "Article Generation Trend",
      "category": "articles"
    },
    {
      "date": "2025-10-30",
      "value": 0,
      "label": "Article Generation Trend",
      "category": "articles"
    },
    {
      "date": "2025-10-31",
      "value": 0,
      "label": "Article Generation Trend",
      "category": "articles"
    },
    {
      "date": "2025-11-01",
      "value": 0,
      "label": "Article Generation Trend",
      "category": "articles"
    },
    {
      "date": "2025-11-02",
      "value": 0,
      "label": "Article Generation Trend",
      "category": "articles"
    },
    {
      "date": "2025-11-03",
      "value": 3,
      "label": "Article Generation Trend",
      "category": "articles"
    },
    {
      "date": "2025-11-04",
      "value": 4,
      "label": "Article Generation Trend",
      "category": "articles"
    },
    {
      "date": "2025-11-05",
      "value": 4,
      "label": "Article Generation Trend",
      "category": "articles"
    },
    {
      "date": "2025-11-06",
      "value": 4,
      "label": "Article Generation Trend",
      "category": "articles"
    },
    {
      "date": "2025-11-07",
      "value": 4,
      "label": "Article Generation Trend",
      "category": "articles"
    },
    {
      "date": "2025-11-08",
      "value": 4,
      "label": "Article Generation Trend",
      "category": "articles"
    },
    {
      "date": "2025-11-09",
      "value": 4,
      "label": "Article Generation Trend",
      "category": "articles"
    },
    {
      "date": "2025-11-10",
      "value": 4,
      "label": "Article Generation Trend",
      "category": "articles"
    },
    {
      "date": "2025-11-11",
      "value": 4,
      "label": "Article Generation Trend",
      "category": "articles"
    },
    {
      "date": "2025-11-12",
      "value": 4,
      "label": "Article Generation Trend",
      "category": "articles"
    },
    {
      "date": "2025-11-13",
      "value": 4,
      "label": "Article Generation Trend",
      "category": "articles"
    },
    {
      "date": "2025-11-14",
      "value": 4,
      "label": "Article Generation Trend",
      "category": "articles"
    },
    {
      "date": "2025-11-15",
      "value": 4,
      "label": "Article Generation Trend",
      "category": "articles"
    },
    {
      "date": "2025-11-16",
      "value": 4,
      "label": "Article Generation Trend",
      "category": "articles"
    },
    {
      "date": "2025-11-17",
      "value": 4,
      "label": "Article Generation Trend",
      "category": "articles"
    },
    {
      "date": "2025-11-18",
      "value": 4,
      "label": "Article Generation Trend",
      "category": "articles"
    },
    {
      "date": "2025-11-19",
      "value": 4,
      "label": "Article Generation Trend",
      "category": "articles"
    },
    {
      "date": "2025-11-20",
      "value": 4,
      "label": "Article Generation Trend",
      "category": "articles"
    },
    {
      "date": "2025-11-21",
      "value": 4,
      "label": "Article Generation Trend",
      "category": "articles"
    },
    {
      "date": "2025-11-22",
      "value": 4,
      "label": "Article Generation Trend",
      "category": "articles"
    },
    {
      "date": "2025-11-23",
      "value": 4,
      "label": "Article Generation Trend",
      "category": "articles"
    },
    {
      "date": "2025-11-24",
      "value": 4,
      "label": "Article Generation Trend",
      "category": "articles"
    },
    {
      "date": "2025-11-25",
      "value": 4,
      "label": "Article Generation Trend",
      "category": "articles"
    },
    {
      "date": "2025-11-26",
      "value": 4,
      "label": "Article Generation Trend",
      "category": "articles"
    }
  ],
  "last_updated": "2025-11-27T19:37:44.761017Z",
  "trend_direction": "up"
}